xlcompare/__init__.py
xlcompare/__main__.py
xlcompare/xlcompare.py
xlcompare-0.2.0.dist-info/LICENSE
xlcompare-0.2.0.dist-info/METADATA
xlcompare-0.2.0.dist-info/WHEEL
xlcompare-0.2.0.dist-info/entry_points.txt
xlcompare-0.2.0.dist-info/top_level.txt
xlcompare-0.2.0.dist-info/RECORD
