Metadata-Version: 2.1
Name: xlcompare
Version: 0.2.0
Summary: Compare two Excel files where rows have unique identifiers.
Home-page: https://github.com/ravi-chandran/xlcompare
Author: Ravi Chandran
License: UNKNOWN
Platform: UNKNOWN
Classifier: Programming Language :: Python :: 3
Classifier: License :: OSI Approved :: MIT License
Classifier: Operating System :: OS Independent
Requires-Python: >=3.6
Requires-Dist: xlrd (>=2.0.1)
Requires-Dist: pylightxl (>=1.54)
Requires-Dist: XlsxWriter (>=1.3.9)
